Metadata-Version: 2.1
Name: PDEDA
Version: 0.0.2
Summary: Automate Exploratory Data Analysis
Home-page: https://github.com/vishalbpatil1/plotly-dash-eda
Author: Vishal Patil
Author-email: vishalbpatil1@gmail.com
License: MIT
Keywords: Exploratory Data Analysis
Platform: UNKNOWN
Classifier: License :: OSI Approved :: MIT License
Classifier: Programming Language :: Python :: 3
Classifier: Programming Language :: Python :: 3.7
Classifier: Programming Language :: Python :: 3.8
